cas_visualizer/__init__.py
cas_visualizer/util.py
cas_visualizer/visualizer.py
cas_visualizer-0.1.5.dist-info/LICENSE
cas_visualizer-0.1.5.dist-info/METADATA
cas_visualizer-0.1.5.dist-info/WHEEL
cas_visualizer-0.1.5.dist-info/RECORD
