Metadata-Version: 2.1
Name: cas-visualizer
Version: 0.1.5
Summary: 
License: MIT
Author: Torsten Zesch
Author-email: torsten.zesch@gmail.com
Requires-Python: >=3.11.0,<4.0.0
Classifier: License :: OSI Approved :: MIT License
Classifier: Programming Language :: Python :: 3
Classifier: Programming Language :: Python :: 3.11
Classifier: Programming Language :: Python :: 3.12
Classifier: Programming Language :: Python :: 3.13
Requires-Dist: dkpro-cassis (>=0.10.0)
Requires-Dist: pandas (>=1.3.0)
Requires-Dist: spacy (>=3.2.0)
